MySimpleDB-1.0.dist-info/DESCRIPTION.rst
MySimpleDB-1.0.dist-info/METADATA
MySimpleDB-1.0.dist-info/RECORD
MySimpleDB-1.0.dist-info/WHEEL
MySimpleDB-1.0.dist-info/metadata.json
MySimpleDB-1.0.dist-info/top_level.txt
mysimpledb/__init__.py
mysimpledb/db.py
